{
  "restaurant": [
    {
      "precioPlatillo": "200",
      "nombrePlatillo": "Cheesecake",
      "categoria": "postre",
      "id": 1
    },
    {
      "precioPlatillo": "300",
      "nombrePlatillo": "Rib eye 400g",
      "categoria": "cortes",
      "id": 2
    },
    {
      "nombrePlatillo": "Ensalada",
      "precioPlatillo": "100",
      "categoria": "ensalada",
      "id": 3
    },
    {
      "precioPlatillo": "300",
      "nombrePlatillo": "Bife de chorizo",
      "categoria": "cortes",
      "id": 4
    },
    {
      "precioPlatillo": "70",
      "nombrePlatillo": "Pie de limon",
      "categoria": "postre",
      "id": 5
    },
    {
      "precioPlatillo": "100",
      "nombrePlatillo": "Budin de banana",
      "categoria": "postre",
      "id": 6
    },
    {
      "nombrePlatillo": "Asado",
      "precioPlatillo": "400",
      "categoria": "cortes",
      "id": 7
    },
    {
      "nombrePlatillo": "Ensalada de pollo",
      "precioPlatillo": "250",
      "categoria": "ensalada",
      "id": 8
    },
    {
      "precioPlatillo": "150",
      "nombrePlatillo": "Limonada",
      "categoria": "bebida",
      "id": 9
    }
  ]
}